core/__init__.py
core/algorithnm/Algorithm.py
core/algorithnm/GBP.py
core/algorithnm/GradCAM.py
core/algorithnm/GuidedGradCAM.py
core/algorithnm/IntegratedGradient.py
core/algorithnm/LIME.py
core/algorithnm/SaliencyMap.py
core/algorithnm/Sensitivity.py
core/algorithnm/SmoothGrad.py
core/algorithnm/__init__.py
core/algorithnm/utils.py
core/datasets/CIFAR.py
core/datasets/DataSet.py
core/datasets/DataSets.py
core/datasets/MNIST.py
core/datasets/SVHN.py
core/datasets/__init__.py
core/datasets/flowers.py
core/logger/ColoredLogger.py
core/logger/Logger.py
core/logger/__init__.py
core/metrics/ConfuseMatrix.py
core/metrics/Metrics.py
core/metrics/__init__.py
core/model/Models.py
core/model/ResNet.py
core/model/__init__.py
core/train/Train.py
core/train/__init__.py
core/visualize/__init__.py
trainer/Trainer.py
trainer/__init__.py
vinn/__init__.py
vinn/algorithnm/Algorithm.py
vinn/algorithnm/GBP.py
vinn/algorithnm/GradCAM.py
vinn/algorithnm/GuidedGradCAM.py
vinn/algorithnm/IntegratedGradient.py
vinn/algorithnm/LIME.py
vinn/algorithnm/SaliencyMap.py
vinn/algorithnm/Sensitivity.py
vinn/algorithnm/SmoothGrad.py
vinn/algorithnm/__init__.py
vinn/algorithnm/utils.py
vinn/datasets/CIFAR.py
vinn/datasets/DataSet.py
vinn/datasets/MNIST.py
vinn/datasets/SVHN.py
vinn/datasets/__init__.py
vinn/datasets/flowers.py
vinn/logger/ColoredLogger.py
vinn/logger/Logger.py
vinn/logger/__init__.py
vinn/metrics/ConfuseMatrix.py
vinn/metrics/Metrics.py
vinn/metrics/__init__.py
vinn/model/Models.py
vinn/model/ResNet.py
vinn/model/__init__.py
vinn/train/Train.py
vinn/train/__init__.py
vinn/trainer/Trainer.py
vinn/trainer/__init__.py
vinn/visualize/__init__.py
vinn-1.1.dist-info/METADATA
vinn-1.1.dist-info/WHEEL
vinn-1.1.dist-info/top_level.txt
vinn-1.1.dist-info/RECORD
