Metadata-Version: 2.1
Name: vinn
Version: 1.1
Summary: Visual Interpretation of Neural Networks
Home-page: https://github.com/Torato-Taraka/VINN
Author: qianzhihao
Author-email: 2018302170027@whu.edu.cn
License: UNKNOWN
Platform: UNKNOWN
Classifier: Programming Language :: Python :: 3
Classifier: License :: OSI Approved :: MIT License
Classifier: Operating System :: OS Independent
